flask_req_parser/__init__.py
flask_req_parser-0.1.4.dist-info/LICENSE
flask_req_parser-0.1.4.dist-info/METADATA
flask_req_parser-0.1.4.dist-info/WHEEL
flask_req_parser-0.1.4.dist-info/top_level.txt
flask_req_parser-0.1.4.dist-info/RECORD
