Metadata-Version: 2.1
Name: flask-req-parser
Version: 0.1.4
Summary: Simple Request parser for flask
Home-page: https://github.com/Rhyanz46/flask-req-parser
Author: Arian Saputra
Author-email: rianariansaputra@gmail.com
License: BSD
Platform: any
Classifier: Environment :: Web Environment
Classifier: Intended Audience :: Developers
Classifier: License :: OSI Approved :: BSD License
Classifier: Operating System :: OS Independent
Classifier: Programming Language :: Python
Classifier: Topic :: Internet :: WWW/HTTP :: Dynamic Content
Classifier: Topic :: Software Development :: Libraries :: Python Modules
Requires-Dist: Flask
